WUADS/__init__.py
WUADS/aircraft.py
WUADS/avl_run.py
WUADS/flight_conditions.py
WUADS/mission.py
WUADS/mission_segments.py
WUADS/propulsion.py
WUADS/reports.py
WUADS/assets/737-800.yml
WUADS/assets/__init__.py
WUADS/assets/naca_0012.dat
WUADS/assets/nacelle.stl
WUADS/assets/rae2822.dat
WUADS/assets/__pycache__/__init__.cpython-310.pyc
WUADS/components/__init__.py
WUADS/components/component.py
WUADS/components/subsystems.py
WUADS/components/usefulload.py
WUADS/components/aerobodies/__init__.py
WUADS/components/aerobodies/engine.py
WUADS/components/aerobodies/fuselage.py
WUADS/components/aerobodies/horizontal.py
WUADS/components/aerobodies/vertical.py
WUADS/components/aerobodies/wing.py
WUADS/components/aerobodies/wing_advanced.py
WUADS/components/aerobodies/wing_yehudi.py
WUADS/gui/__init__.py
WUADS/gui/graphics.py
WUADS/gui/main.py
WUADS/gui/main_window.py
WUADS/gui/toolbox/__init__.py
WUADS/gui/toolbox/aircraft_info.py
WUADS/gui/toolbox/analysis_list.py
WUADS/gui/toolbox/component_edit.py
WUADS/gui/toolbox/mission_profile_edit.py
WUADS/gui/toolbox/propulsion_input.py
WUADS/gui/toolbox/subcomponent_edit.py
WUADS/gui/toolbox/toolbox_main.py
WUADS/gui/toolbox/useful_load_edit.py
wuads-0.2.24.dist-info/licenses/LICENSE
wuads-0.2.24.dist-info/METADATA
wuads-0.2.24.dist-info/WHEEL
wuads-0.2.24.dist-info/entry_points.txt
wuads-0.2.24.dist-info/top_level.txt
wuads-0.2.24.dist-info/RECORD
