Metadata-Version: 2.4
Name: WUADS
Version: 0.2.24
Summary: Conceptual aircraft design package with empirical and numerical methods
License: Mozilla Public License
Requires-Python: >=3.8
License-File: LICENSE
Requires-Dist: pyside6
Requires-Dist: pyvista
Requires-Dist: pyvistaqt
Requires-Dist: numpy
Requires-Dist: scipy
Requires-Dist: pyyaml
Requires-Dist: pandas
Requires-Dist: openpyxl
Dynamic: license-file
